cppython_conan/__init__.py
cppython_conan/plugin.py
cppython_conan/py.typed
cppython_conan/resolution.py
cppython_conan/schema.py
cppython_conan-0.0.2.dev2.dist-info/entry_points.txt
cppython_conan-0.0.2.dev2.dist-info/WHEEL
cppython_conan-0.0.2.dev2.dist-info/METADATA
cppython_conan-0.0.2.dev2.dist-info/licenses/LICENSE.md
cppython_conan-0.0.2.dev2.dist-info/RECORD
