Metadata-Version: 2.1
Name: cppython-conan
Version: 0.0.2.dev2
Summary: Conan provider for CPPython
License: MIT
Author-email: Synodic Software <contact@synodic.software>
Requires-Python: >=3.11
Requires-Dist: conan>=2.0.0-beta4
Requires-Dist: cppython-core>=0.3.3.dev0
Project-URL: homepage, https://github.com/Synodic-Software/CPPython-Conan
Project-URL: repository, https://github.com/Synodic-Software/CPPython-Conan
